README.rst
setup.py
cauldron/__init__.py
cauldron/redis_cache.py
cauldron/sql.py
cauldron.egg-info/PKG-INFO
cauldron.egg-info/SOURCES.txt
cauldron.egg-info/dependency_links.txt
cauldron.egg-info/pbr.json
cauldron.egg-info/requires.txt
cauldron.egg-info/top_level.txt