Metadata-Version: 1.0
Name: cauldron
Version: 1.0.14
Summary: Utils to reduce boilerplate code
Home-page: https://github.com/nerandell/cauldron
Author: Ankit Chandawala
Author-email: ankitchandawala@gmail.com
License: UNKNOWN
Platform: UNKNOWN
